[

{"title": "Chapter 1",
"key": "Mishnah/Commentary/Rambam/Rambam on Mishnah Eruvin/Chapter 1",
"id": "Mishnah.Commentary.Rambam.Rambam_on_Mishnah_Eruvin.1",
"children": [

{"title": "Mishna 1",
"key": "Mishnah/Commentary/Rambam/Rambam on Mishnah Eruvin/Chapter 1/Mishna 1",
"id": "Mishnah.Commentary.Rambam.Rambam_on_Mishnah_Eruvin.1.1",
"children": [

{"title": "Comment 1",
"key": "Mishnah/Commentary/Rambam/Rambam on Mishnah Eruvin/Chapter 1/Mishna 1/Comment 1",
"id": "Mishnah.Commentary.Rambam.Rambam_on_Mishnah_Eruvin.1.1.1",
"children": []}]}]}]